AUTHORS
LICENSE
MANIFEST.in
ez_setup.py
setup.py
bin/sopex
sopex/__init__.py
sopex/__init__.pyc
sopex/chunker.py
sopex/chunker.pyc
sopex/extractor.py
sopex/extractor.pyc
sopex.egg-info/PKG-INFO
sopex.egg-info/SOURCES.txt
sopex.egg-info/dependency_links.txt
sopex.egg-info/requires.txt
sopex.egg-info/top_level.txt
sopex/jars/englishPCFG-model.jar
sopex/jars/stanford-parser.jar