Metadata-Version: 1.0
Name: sopex
Version: 0.1
Summary: Library and CLI to extract the subject, predicate and object for a given english sentence
Home-page: https://github.com/codemaniac/sopex
Author: Ashish Prasad (codemaniac)
Author-email: ashish.ap.rao@gmail.com
License: LICENSE
Keywords: NLP subject predicate object triplet extraction
Platform: UNKNOWN
